Metadata-Version: 1.1
Name: ptodbc
Version: 0.0.1
Summary: get odbc with username and password
Home-page: UNKNOWN
Author: Zheng Xu
Author-email: chizetas@gmail.com
License: MIT
Keywords: Pioneer Tools odbc
Platform: UNKNOWN
Classifier: Development Status :: 5 - Production/Stable
Classifier: Intended Audience :: Education
Classifier: Operating System :: Microsoft :: Windows :: Windows 10
Classifier: License :: OSI Approved :: MIT License
Classifier: Programming Language :: Python :: 3
